pyams_chat_ws/__init__.py
pyams_chat_ws/app.py
pyams_chat_ws/auth.py
pyams_chat_ws/chat.py
pyams_chat_ws/monitor.py
pyams_chat_ws/webapp.py
pyams_chat_ws-2.0.1.dist-info/LICENSE
pyams_chat_ws-2.0.1.dist-info/METADATA
pyams_chat_ws-2.0.1.dist-info/WHEEL
pyams_chat_ws-2.0.1.dist-info/namespace_packages.txt
pyams_chat_ws-2.0.1.dist-info/top_level.txt
pyams_chat_ws-2.0.1.dist-info/RECORD
