Metadata-Version: 2.1
Name: pyams-chat-ws
Version: 2.0.1
Summary: PyAMS chat async server
Home-page: https://pyams.readthedocs.io
Author: Thierry Florac
Author-email: tflorac@ulthar.net
License: ZPL
Keywords: Pyramid PyAMS
Classifier: License :: OSI Approved :: Zope Public License
Classifier: Development Status :: 4 - Beta
Classifier: Programming Language :: Python
Classifier: Framework :: Pyramid
Classifier: Topic :: Software Development :: Libraries :: Python Modules
License-File: LICENSE
Requires-Dist: setuptools
Requires-Dist: async-timeout
Requires-Dist: httpx
Requires-Dist: redis
Requires-Dist: starlette
Requires-Dist: websockets
Provides-Extra: test
